packaging_workshop/__init__.py
packaging_workshop/add.py
packaging_workshop-0.1.0.dist-info/METADATA
packaging_workshop-0.1.0.dist-info/WHEEL
packaging_workshop-0.1.0.dist-info/entry_points.txt
packaging_workshop-0.1.0.dist-info/RECORD
