Metadata-Version: 2.4
Name: packaging-workshop
Version: 0.1.0
Summary: Add your description here
Author-email: ChristinaPapastolopoulou <papastolopoulou@gmail.com>
Requires-Python: >=3.8
Requires-Dist: pytest>=8.3.5
Requires-Dist: ruff>=0.11.2
